v/led_driver.v
/*
 * Code placed in public domain.
 */

`timescale 10ns/100ps

module led_driver(
    input wire clk,
    input wire reset__disable,
    output reg reset__ack,
    output reg led);

    /*
     * Locally managed data:
     */
    reg [11:0] counter;
    reg [11:0] thresh;

    /*
     * Logic for this module:
     */
    always @(posedge clk)
      begin
        reset__ack <= #1 ~ reset__disable;
        if (! reset__disable)
          begin
            led <= #1 1'b0;
            thresh <= #1 12'H1;
            counter <= #1 12'H0;
          end
        else if (thresh == counter)
          begin
            led <= #1 ~ led;
            counter <= #1 12'H0;
            thresh <= #1 (thresh + 12'H3);
          end
        else
          begin
            counter <= #1 (counter + 12'H1);
          end
      end

endmodule /* led_driver */

v/led_driver_test.v
/*
 * Code placed in public domain.
 */

`timescale 10ns/100ps

module led_driver_test();

    /*
     * Locally managed data:
     */
    wire clk;
    wire led;
    reg reset__disable;
    wire reset__ack;
    reg [11:0] script;

    /*
     * Inner modules referenced by this module:
     *
     * => led_driver
     */

    led_driver target(
        clk,

        reset__disable,
        reset__ack,

        led);


    /*
     * Logic for this module:
     */
    assign clk = script[1];

    initial
      begin
        $dumpvars();
        reset__disable <= #1 1'b1;
        script <= #1 12'H0;
      end

    always @(posedge clk, script)
      begin
        script <= #1 (script + 12'H1);
        case (script)
        12'H6:
          begin
            reset__disable <= #1 1'b0;
          end
        12'H14:
          begin
            if (! reset__ack)
              begin
                $display("led.bb(51):RESULT=FAIL:1 @ testing failed reset ack");
                $finish_and_return(1);
              end
            reset__disable <= #1 1'b1;
          end
        12'H12c:
          begin
            $display("led.bb(56):RESULT=PASS:0 @ testing completed");
            $finish_and_return(0);
          end
        endcase
      end


endmodule /* led_driver_test */

v/dump.vcd
$date
	Sat Dec 31 14:24:11 2022
$end
$version
	Icarus Verilog
$end
$timescale
	100ps
$end
$scope module led_driver_test $end
$var wire 1 ! reset__ack $end
$var wire 1 " led $end
$var wire 1 # clk $end
$var reg 1 $ reset__disable $end
$var reg 12 % script [11:0] $end
$scope module target $end
$var wire 1 # clk $end
$var wire 1 $ reset__disable $end
$var reg 12 & counter [11:0] $end
$var reg 1 " led $end
$var reg 1 ! reset__ack $end
$var reg 12 ' thresh [11:0] $end
$upscope $end
$upscope $end
$enddefinitions $end
#0
$dumpvars
bx '
bx &
bx %
x$
x#
x"
x!
$end
#100
0#
b0 %
1$
#200
b1 %
#300
1#
b10 %
#400
0!
b11 %
#500
0#
b100 %
#600
b101 %
#700
1#
b110 %
#800
0$
b111 %
#900
0#
b1000 %
#1000
b1001 %
#1100
1#
b1010 %
#1200
b0 &
b1 '
0"
1!
b1011 %
#1300
0#
b1100 %
#1400
b1101 %
#1500
1#
b1110 %
#1600
b1111 %
#1700
0#
b10000 %
#1800
b10001 %
#1900
1#
b10010 %
#2000
b10011 %
#2100
0#
b10100 %
#2200
1$
b10101 %
#2300
1#
b10110 %
#2400
b1 &
0!
b10111 %
#2500
0#
b11000 %
#2600
b11001 %
#2700
1#
b11010 %
#2800
b100 '
b0 &
1"
b11011 %
#2900
0#
b11100 %
#3000
b11101 %
#3100
1#
b11110 %
#3200
b1 &
b11111 %
#3300
0#
b100000 %
#3400
b100001 %
#3500
1#
b100010 %
#3600
b10 &
b100011 %
#3700
0#
b100100 %
#3800
b100101 %
#3900
1#
b100110 %
#4000
b11 &
b100111 %
#4100
0#
b101000 %
#4200
b101001 %
#4300
1#
b101010 %
#4400
b100 &
b101011 %
#4500
0#
b101100 %
#4600
b101101 %
#4700
1#
b101110 %
#4800
b111 '
b0 &
0"
b101111 %
#4900
0#
b110000 %
#5000
b110001 %
#5100
1#
b110010 %
#5200
b1 &
b110011 %
#5300
0#
b110100 %
#5400
b110101 %
#5500
1#
b110110 %
#5600
b10 &
b110111 %
#5700
0#
b111000 %
#5800
b111001 %
#5900
1#
b111010 %
#6000
b11 &
b111011 %
#6100
0#
b111100 %
#6200
b111101 %
#6300
1#
b111110 %
#6400
b100 &
b111111 %
#6500
0#
b1000000 %
#6600
b1000001 %
#6700
1#
b1000010 %
#6800
b101 &
b1000011 %
#6900
0#
b1000100 %
#7000
b1000101 %
#7100
1#
b1000110 %
#7200
b110 &
b1000111 %
#7300
0#
b1001000 %
#7400
b1001001 %
#7500
1#
b1001010 %
#7600
b111 &
b1001011 %
#7700
0#
b1001100 %
#7800
b1001101 %
#7900
1#
b1001110 %
#8000
b1010 '
b0 &
1"
b1001111 %
#8100
0#
b1010000 %
#8200
b1010001 %
#8300
1#
b1010010 %
#8400
b1 &
b1010011 %
#8500
0#
b1010100 %
#8600
b1010101 %
#8700
1#
b1010110 %
#8800
b10 &
b1010111 %
#8900
0#
b1011000 %
#9000
b1011001 %
#9100
1#
b1011010 %
#9200
b11 &
b1011011 %
#9300
0#
b1011100 %
#9400
b1011101 %
#9500
1#
b1011110 %
#9600
b100 &
b1011111 %
#9700
0#
b1100000 %
#9800
b1100001 %
#9900
1#
b1100010 %
#10000
b101 &
b1100011 %
#10100
0#
b1100100 %
#10200
b1100101 %
#10300
1#
b1100110 %
#10400
b110 &
b1100111 %
#10500
0#
b1101000 %
#10600
b1101001 %
#10700
1#
b1101010 %
#10800
b111 &
b1101011 %
#10900
0#
b1101100 %
#11000
b1101101 %
#11100
1#
b1101110 %
#11200
b1000 &
b1101111 %
#11300
0#
b1110000 %
#11400
b1110001 %
#11500
1#
b1110010 %
#11600
b1001 &
b1110011 %
#11700
0#
b1110100 %
#11800
b1110101 %
#11900
1#
b1110110 %
#12000
b1010 &
b1110111 %
#12100
0#
b1111000 %
#12200
b1111001 %
#12300
1#
b1111010 %
#12400
b1101 '
b0 &
0"
b1111011 %
#12500
0#
b1111100 %
#12600
b1111101 %
#12700
1#
b1111110 %
#12800
b1 &
b1111111 %
#12900
0#
b10000000 %
#13000
b10000001 %
#13100
1#
b10000010 %
#13200
b10 &
b10000011 %
#13300
0#
b10000100 %
#13400
b10000101 %
#13500
1#
b10000110 %
#13600
b11 &
b10000111 %
#13700
0#
b10001000 %
#13800
b10001001 %
#13900
1#
b10001010 %
#14000
b100 &
b10001011 %
#14100
0#
b10001100 %
#14200
b10001101 %
#14300
1#
b10001110 %
#14400
b101 &
b10001111 %
#14500
0#
b10010000 %
#14600
b10010001 %
#14700
1#
b10010010 %
#14800
b110 &
b10010011 %
#14900
0#
b10010100 %
#15000
b10010101 %
#15100
1#
b10010110 %
#15200
b111 &
b10010111 %
#15300
0#
b10011000 %
#15400
b10011001 %
#15500
1#
b10011010 %
#15600
b1000 &
b10011011 %
#15700
0#
b10011100 %
#15800
b10011101 %
#15900
1#
b10011110 %
#16000
b1001 &
b10011111 %
#16100
0#
b10100000 %
#16200
b10100001 %
#16300
1#
b10100010 %
#16400
b1010 &
b10100011 %
#16500
0#
b10100100 %
#16600
b10100101 %
#16700
1#
b10100110 %
#16800
b1011 &
b10100111 %
#16900
0#
b10101000 %
#17000
b10101001 %
#17100
1#
b10101010 %
#17200
b1100 &
b10101011 %
#17300
0#
b10101100 %
#17400
b10101101 %
#17500
1#
b10101110 %
#17600
b1101 &
b10101111 %
#17700
0#
b10110000 %
#17800
b10110001 %
#17900
1#
b10110010 %
#18000
b10000 '
b0 &
1"
b10110011 %
#18100
0#
b10110100 %
#18200
b10110101 %
#18300
1#
b10110110 %
#18400
b1 &
b10110111 %
#18500
0#
b10111000 %
#18600
b10111001 %
#18700
1#
b10111010 %
#18800
b10 &
b10111011 %
#18900
0#
b10111100 %
#19000
b10111101 %
#19100
1#
b10111110 %
#19200
b11 &
b10111111 %
#19300
0#
b11000000 %
#19400
b11000001 %
#19500
1#
b11000010 %
#19600
b100 &
b11000011 %
#19700
0#
b11000100 %
#19800
b11000101 %
#19900
1#
b11000110 %
#20000
b101 &
b11000111 %
#20100
0#
b11001000 %
#20200
b11001001 %
#20300
1#
b11001010 %
#20400
b110 &
b11001011 %
#20500
0#
b11001100 %
#20600
b11001101 %
#20700
1#
b11001110 %
#20800
b111 &
b11001111 %
#20900
0#
b11010000 %
#21000
b11010001 %
#21100
1#
b11010010 %
#21200
b1000 &
b11010011 %
#21300
0#
b11010100 %
#21400
b11010101 %
#21500
1#
b11010110 %
#21600
b1001 &
b11010111 %
#21700
0#
b11011000 %
#21800
b11011001 %
#21900
1#
b11011010 %
#22000
b1010 &
b11011011 %
#22100
0#
b11011100 %
#22200
b11011101 %
#22300
1#
b11011110 %
#22400
b1011 &
b11011111 %
#22500
0#
b11100000 %
#22600
b11100001 %
#22700
1#
b11100010 %
#22800
b1100 &
b11100011 %
#22900
0#
b11100100 %
#23000
b11100101 %
#23100
1#
b11100110 %
#23200
b1101 &
b11100111 %
#23300
0#
b11101000 %
#23400
b11101001 %
#23500
1#
b11101010 %
#23600
b1110 &
b11101011 %
#23700
0#
b11101100 %
#23800
b11101101 %
#23900
1#
b11101110 %
#24000
b1111 &
b11101111 %
#24100
0#
b11110000 %
#24200
b11110001 %
#24300
1#
b11110010 %
#24400
b10000 &
b11110011 %
#24500
0#
b11110100 %
#24600
b11110101 %
#24700
1#
b11110110 %
#24800
b10011 '
b0 &
0"
b11110111 %
#24900
0#
b11111000 %
#25000
b11111001 %
#25100
1#
b11111010 %
#25200
b1 &
b11111011 %
#25300
0#
b11111100 %
#25400
b11111101 %
#25500
1#
b11111110 %
#25600
b10 &
b11111111 %
#25700
0#
b100000000 %
#25800
b100000001 %
#25900
1#
b100000010 %
#26000
b11 &
b100000011 %
#26100
0#
b100000100 %
#26200
b100000101 %
#26300
1#
b100000110 %
#26400
b100 &
b100000111 %
#26500
0#
b100001000 %
#26600
b100001001 %
#26700
1#
b100001010 %
#26800
b101 &
b100001011 %
#26900
0#
b100001100 %
#27000
b100001101 %
#27100
1#
b100001110 %
#27200
b110 &
b100001111 %
#27300
0#
b100010000 %
#27400
b100010001 %
#27500
1#
b100010010 %
#27600
b111 &
b100010011 %
#27700
0#
b100010100 %
#27800
b100010101 %
#27900
1#
b100010110 %
#28000
b1000 &
b100010111 %
#28100
0#
b100011000 %
#28200
b100011001 %
#28300
1#
b100011010 %
#28400
b1001 &
b100011011 %
#28500
0#
b100011100 %
#28600
b100011101 %
#28700
1#
b100011110 %
#28800
b1010 &
b100011111 %
#28900
0#
b100100000 %
#29000
b100100001 %
#29100
1#
b100100010 %
#29200
b1011 &
b100100011 %
#29300
0#
b100100100 %
#29400
b100100101 %
#29500
1#
b100100110 %
#29600
b1100 &
b100100111 %
#29700
0#
b100101000 %
#29800
b100101001 %
#29900
1#
b100101010 %
#30000
b1101 &
b100101011 %
#30100
0#
b100101100 %
